{
  "status": "error",
  "note": "CalledProcessError(1, ['yt-dlp', '--remote-components', 'ejs:github', '--cookies', 'youtube_cookies.txt', '--no-playlist', '-f', 'ba/bestaudio', '-x', '--audio-format', 'mp3', '--audio-quality', '7', '-o', 'tmp_audio/老王来了/1sYDmEAosI4.%(ext)s', 'https://www.youtube.com/watch?v=1sYDmEAosI4'])",
  "destination": "老王来了",
  "channel_url": "https://www.youtube.com/@dlw2023",
  "include_members": false,
  "queue_total": 953,
  "queue_index": 459,
  "updated_at": 1775554690,
  "updated_at_readable": "2026-04-07 09:38:10",
  "current_video_id": "1sYDmEAosI4",
  "current_title": "航天丧事喜办隐瞒风险：3位航天员面临巨大危险｜美团内部通知曝光，变成培养李自成张献忠的温床",
  "current_url": "https://www.youtube.com/watch?v=1sYDmEAosI4",
  "current_tab": "streams"
}